sqlonfhir/__init__.py
sqlonfhir/sqlonfhir.py
sqlonfhir-0.0.2.dist-info/WHEEL
sqlonfhir-0.0.2.dist-info/METADATA
sqlonfhir-0.0.2.dist-info/RECORD
