Metadata-Version: 2.3
Name: sqlonfhir
Version: 0.0.2
Summary: Converts FHIR resources to flat formats using SQL on FHIR
Keywords: sqlonfhir,fhir
Author: Stuart Mackle, SAS Healthcare Solutions
Author-email: Stuart Mackle <stuart.mackle@sas.com>, SAS Healthcare Solutions <support@sas.com>
License: Copyright 2025 SAS Institute LLC
Classifier: Programming Language :: Python :: 3.9
Classifier: Programming Language :: Python :: 3.10
Classifier: Programming Language :: Python :: 3.11
Classifier: Operating System :: OS Independent
Requires-Dist: fhirpathpy~=2.1.0
Requires-Dist: pytest==8.4.1 ; extra == 'test'
Requires-Python: >=3.9
Provides-Extra: test
